[
    {
      "id": 1,
      "name": "Introduction to c Programming",
      "img": "https://i.ibb.co/5jT2CNt/Rectangle-2-2.png",
      "price": 49.99,
      "description": "It is a long established fact that a reader will be distracted by the readable content of a page when looking at its layout.",
      "credit": 5
    },
    {
      "id": 2,
      "name": "Introduction to Data Structure",
      "img": "https://i.ibb.co/0ZwzJ3M/Rectangle-3.png",
      "price": 59.99,
      "description": "It is a long established fact that a reader will be distracted by the readable content of a page when looking at its layout.",
      "credit": 8
    },
    {
      "id": 3,
      "name": "Introduction to in c++",
      "img": "https://i.ibb.co/zG7NCtC/Rectangle-2-4.png",
      "price": 79.99,
      "description": "It is a long established fact that a reader will be distracted by the readable content of a page when looking at its layout.",
      
      "credit": 4
    },
    {
      "id": 4,
      "name": "Database (MySQL)",
      "img": "https://i.ibb.co/px3153R/Rectangle-2-1.png",
      "price": 69.99,
      "description": "It is a long established fact that a reader will be distracted by the readable content of a page when looking at its layout.",
   
      "credit": 7
    },
    {
      "id": 5,
      "name": "Introduction to Algorithm",
      "img": "https://i.ibb.co/qpvZ82J/Rectangle-2-3.png",
      "price": 89.99,
      "description": "It is a long established fact that a reader will be distracted by the readable content of a page when looking at its layout.",
      "credit": 6
    },
    {
      "id": 6,
      "name": "Introduction to Advanced Python ",
      "img": "https://i.ibb.co/N7dsnFG/Rectangle-2.png",
      "price": 99.99,
      "description": "It is a long established fact that a reader will be distracted by the readable content of a page when looking at its layout.",
      "credit": 5
    },
    {
      "id": 7,
      "name": "Software Engineering ",
      "img": "https://i.ibb.co/hFdsYLr/Rectangle-2-5.png",
      "price": 49.99,
      "description": "It is a long established fact that a reader will be distracted by the readable content of a page when looking at its layout.",
      "credit": 6
    },
    {
      "id": 8,
      "name": "Problem-Solving Part",
      "img": "https://i.ibb.co/KL9tHXQ/Rectangle-2-6.png",
      "price": 79.99,
      "description": "It is a long established fact that a reader will be distracted by the readable content of a page when looking at its layout.",
      "credit": 10
    },
    {
      "id": 9,
      "name": "AWS, Cloud Computing",
      "img": "https://i.ibb.co/QpxpTvd/Rectangle-3-1.png",
      "price": 59.99,
      "description": "It is a long established fact that a reader will be distracted by the readable content of a page when looking at its layout.",
      "credit": 13
    }
   
  ]